fastapi_cls_controller/__init__.py
fastapi_cls_controller/controller.py
fastapi_cls_controller-0.0.3.dist-info/METADATA
fastapi_cls_controller-0.0.3.dist-info/WHEEL
fastapi_cls_controller-0.0.3.dist-info/top_level.txt
fastapi_cls_controller-0.0.3.dist-info/RECORD
