Metadata-Version: 2.1
Name: fastapi-cls-controller
Version: 0.0.3
Summary: fastapi_cls_controller
Author: Horváth Dániel
Author-email: nitedani@gmail.com
Keywords: fastapi,controller
Classifier: Development Status :: 3 - Alpha
Requires-Dist: fastapi
